coinrule_x_indicators/__init__.py
coinrule_x_indicators/core.py
coinrule_x_indicators/indicators/__init__.py
coinrule_x_indicators/indicators/adx.py
coinrule_x_indicators/indicators/atr.py
coinrule_x_indicators/indicators/bb.py
coinrule_x_indicators/indicators/candle.py
coinrule_x_indicators/indicators/donchian.py
coinrule_x_indicators/indicators/ema.py
coinrule_x_indicators/indicators/liquidation_price.py
coinrule_x_indicators/indicators/price.py
coinrule_x_indicators/indicators/rsi.py
coinrule_x_indicators/indicators/rsi_sma.py
coinrule_x_indicators/indicators/sma.py
coinrule_x_indicators/indicators/unrealized_profit.py
coinrule_x_indicators/indicators/volume_sma.py
coinrule_x_indicators/indicators/webhook_signal.py
coinrule_x_indicators/registry.yaml
coinrule_x_indicators/validation.py
crx_indicators-1.0.0.dist-info/METADATA
crx_indicators-1.0.0.dist-info/WHEEL
crx_indicators-1.0.0.dist-info/entry_points.txt
crx_indicators-1.0.0.dist-info/licenses/LICENSE
crx_indicators-1.0.0.dist-info/RECORD
