Metadata-Version: 2.4
Name: crx-indicators
Version: 1.0.0
Summary: Standard indicators library for the Coinrule X execution platform
License-Expression: MIT
License-File: LICENSE
Keywords: trading,crypto,algo,indicators
Author: Zdenek
Author-email: zdenek@coinrule.com
Requires-Python: >=3.9
Classifier: Development Status :: 3 - Alpha
Classifier: Intended Audience :: Developers
Classifier: Intended Audience :: Financial and Insurance Industry
Classifier: License :: OSI Approved :: MIT License
Classifier: Programming Language :: Python :: 3
Classifier: Programming Language :: Python :: 3.9
Classifier: Programming Language :: Python :: 3.10
Classifier: Programming Language :: Python :: 3.11
Classifier: Topic :: Office/Business :: Financial :: Investment
Requires-Dist: numpy (>=1.20.0)
Requires-Dist: pandas (>=2.0.0)
Requires-Dist: pydantic (>=2.12.5,<3.0.0)
Requires-Dist: pyyaml (>=6.0.3,<7.0.0)
Project-URL: Documentation, https://github.com/coinrule_x/crx-indicators#readme
Project-URL: Issues, https://github.com/coinrule_x/crx-indicators/issues
Project-URL: Source, https://github.com/coinrule_x/crx-indicators
